LICENSE
README.md
pyproject.toml
setup.py
src/highspot/__init__.py
src/highspot/api.py
src/highspot/core.py
src/highspot/domain.py
src/highspot/groups.py
src/highspot/items.py
src/highspot/pitches.py
src/highspot/request.py
src/highspot/spots.py
src/highspot/users.py
src/highspot.egg-info/PKG-INFO
src/highspot.egg-info/SOURCES.txt
src/highspot.egg-info/dependency_links.txt
src/highspot.egg-info/requires.txt
src/highspot.egg-info/top_level.txt
src/highspot/errors/__init__.py
src/highspot/errors/exceptions.py
src/highspot/errors/handlers.py
src/highspot/utils/__init__.py
src/highspot/utils/log_utils.py
src/highspot/utils/version.py